wolflive/__init__.py
wolflive/client.py
wolflive/exceptions.py
wolflive/sync_adapter.py
wolflive/utils.py
wolflive-0.0.1.dist-info/licenses/LICENSE
wolflive-0.0.1.dist-info/METADATA
wolflive-0.0.1.dist-info/WHEEL
wolflive-0.0.1.dist-info/top_level.txt
wolflive-0.0.1.dist-info/RECORD
